sqlite_dataset/__init__.py
sqlite_dataset/dataset.py
sqlite_dataset/fields.py
sqlite_dataset/test.py
sqlite_dataset/utils.py
sqlite_dataset-0.5.1.dist-info/LICENSE
sqlite_dataset-0.5.1.dist-info/METADATA
sqlite_dataset-0.5.1.dist-info/WHEEL
sqlite_dataset-0.5.1.dist-info/RECORD
