Metadata-Version: 2.1
Name: sqlite-dataset
Version: 0.5.1
Summary: Use SQLite database to store datasets.
Home-page: https://github.com/Mayazure/sqlite-dataset
License: MIT
Author: Jinshuai Ma
Author-email: mayazureee@gmail.com
Requires-Python: >=3.7,<4.0
Classifier: License :: OSI Approved :: MIT License
Classifier: Programming Language :: Python :: 3
Classifier: Programming Language :: Python :: 3.7
Classifier: Programming Language :: Python :: 3.8
Classifier: Programming Language :: Python :: 3.9
Classifier: Programming Language :: Python :: 3.10
Classifier: Programming Language :: Python :: 3.11
Requires-Dist: sqlalchemy (>=1.3.0)
Project-URL: Repository, https://github.com/Mayazure/sqlite-dataset
